[
  {     "fecha": "2026/04/15",     "hora": "19:00",     "zkia": "2",     "fronton": "Irurtzun – Bi Ahizpe",     "etxekoa": "LARRAUN (Astiz – Sotil) ",     "kanpokoak": "HERNANI (Apaolaza – Balerdi)",     "lehiaketa": "IRURTZUNGO PILOTA TXAPELKETA. HELDUAK KANPORAKETA",     "ofiziala": "false"   },
  {     "fecha": "2026/04/16",     "hora": "18:30",     "zkia": "4",     "fronton": "Lesaka",     "etxekoa": "ALDE ZAHARRA (I. Atxa)",     "kanpokoak": "LARRAUN (J. Ezkurdia)",     "lehiaketa": "BENITO TAINTA MEMORIALA 4 ½. HELDUAK KANPORAKETA",     "ofiziala": "false"   },
  {     "fecha": "2026/04/19",     "hora": "09:30",     "zkia": "2",     "fronton": "Lesaka",     "etxekoa": "LARRAUN (X. Goldarazena)",     "kanpokoak": "BURUZGAIN (E. Alsua)",     "lehiaketa": "BENITO TAINTA MEMORIALA 4 ½. HAURRAK KANPORAKETA",     "ofiziala": "false"   },
  {     "fecha": "2026/04/19",     "hora": "10:00",     "zkia": "4",     "fronton": "Elizondo",     "etxekoa": "SAN ASENSIO – NAJERA (Nanclares – Gomez)",     "kanpokoak": "AZPEITI – LARRAUN (Arsuaga – Oreja)",     "lehiaketa": "BAZTANGO UDABERRI TXAPELKETA. GAZTEAK FINAL ERDIAK",     "ofiziala": "false"   },
  {     "fecha": "2026/04/19",     "hora": "17:30",     "zkia": "2",     "fronton": "Najera",     "etxekoa": "BURUZGAIN – LARRAUN (Aldaz – Tellechea)",     "kanpokoak": "",     "lehiaketa": "TORNEO REINO DE NAJERA. PROMESAS FINAL LAURDENAK",     "ofiziala": "false"   }

]
