[ 
  {
    "fecha": "2026-01-09",
    "fronton": "Elgoibar",
    "etxekoa": "Nazabal (LARRAUN) – Artetxe",
    "kanpokoak": "Izagirre – Ormatxea",
    "tanteoa": "17-22",
    "sets": [""],
    "modalidad": "SAN ANTON PILOTA TXAPELKETA. PROMESA MUTILAK. FINALAURREKOA",
    "emaitza": "17-22",
    "ofiziala": "false",
    "url": "-"
  },
  {
    "fecha": "2026-01-10",
    "fronton": "Pamplona – Oberena 2",
    "etxekoa": "OBERENA", 
    "kanpokoak": "LARRAUN",
    "tanteoa": "2-0",
    "sets": [],
    "modalidad": "ESPAINAKO TXAPELKETA OHOREZKO MAILA ",
    "emaitza": "galduta",
    "ofiziala": "true",
    "url": "https://www.facebook.com/photo/?fbid=1498635188931107&set=pcb.1498635358931090"
  }
]
